bitinformation/__init__.py
bitinformation/analyser.py
bitinformation/icont.py
bitinformation/parameters.py
bitinformation/preprocessor.py
bitinformation/simple_packing.py
bitinformation/statistics.py
bitinformation/table.py
bitinformation/tool.py
bitinformation-0.1.1.dist-info/METADATA
bitinformation-0.1.1.dist-info/WHEEL
bitinformation-0.1.1.dist-info/licenses/LICENSE
bitinformation-0.1.1.dist-info/RECORD
