Metadata-Version: 2.1
Name: bitinformation
Version: 0.1.1
Summary: Bitwise information content computation
Project-URL: Homepage, https://git.ecmwf.int/users/maee/repos/bitinformation/browse
Author-email: Eugen Betke <eugen.betke@ecmwf.int>
License-Expression: GPL-3.0-or-later
License-File: LICENSE
Classifier: License :: OSI Approved :: GNU General Public License v3 or later (GPLv3+)
Classifier: Operating System :: OS Independent
Classifier: Programming Language :: Python :: 3
Requires-Python: >=3.7
Requires-Dist: numpy>=1.23.1
Requires-Dist: pandas>=1.5.1
Requires-Dist: pyyaml>=6.0
Requires-Dist: scipy>=1.9.3
